Metadata-Version: 2.1
Name: brer-md
Version: 2.0.0b9
Summary: A set of scripts for running BRER simulations using gmxapi.
Author: Jennifer M. Hays, Kasson Lab BRER Team
Author-email: Kasson Lab BRER Team <kassonlab@gmail.com>
License: LGPL 2.1
Project-URL: Source, https://github.com/kassonlab/brer-md/
Project-URL: Documentation, https://kassonlab.github.io/brer-md/
Classifier: License :: OSI Approved :: GNU Lesser General Public License v2 or later (LGPLv2+)
Classifier: Programming Language :: Python :: 3
Requires-Python: >=3.8
Provides-Extra: test
License-File: LICENSE
